dopamax/__init__.py
dopamax/callbacks.py
dopamax/distributions.py
dopamax/networks.py
dopamax/prioritized_item_buffer.py
dopamax/rollouts.py
dopamax/spaces.py
dopamax/typing.py
dopamax/utils.py
dopamax/_scripts/__init__.py
dopamax/_scripts/cli.py
dopamax/agents/__init__.py
dopamax/agents/base.py
dopamax/agents/utils.py
dopamax/agents/anakin/__init__.py
dopamax/agents/anakin/alphazero.py
dopamax/agents/anakin/base.py
dopamax/agents/anakin/ddpg.py
dopamax/agents/anakin/dqn.py
dopamax/agents/anakin/ppo.py
dopamax/agents/anakin/sac.py
dopamax/agents/anakin/utils.py
dopamax/environments/__init__.py
dopamax/environments/environment.py
dopamax/environments/gymnax.py
dopamax/environments/utils.py
dopamax/environments/visualization.py
dopamax/environments/brax/__init__.py
dopamax/environments/brax/ant.py
dopamax/environments/brax/base.py
dopamax/environments/brax/half_cheetah.py
dopamax/environments/brax/inverted_pendulum.py
dopamax/environments/pgx/__init__.py
dopamax/environments/pgx/base.py
dopamax/environments/pgx/chess.py
dopamax/environments/pgx/connect_four.py
dopamax/environments/pgx/go.py
dopamax/environments/pgx/tic_tac_toe.py
dopamax-0.2.1.dist-info/LICENSE
dopamax-0.2.1.dist-info/METADATA
dopamax-0.2.1.dist-info/WHEEL
dopamax-0.2.1.dist-info/entry_points.txt
dopamax-0.2.1.dist-info/top_level.txt
dopamax-0.2.1.dist-info/RECORD
