Metadata-Version: 2.2
Name: dopamax
Version: 0.2.1
Summary: Reinforcement learning in pure JAX.
Author-email: Ryan Strauss <ryanrstrauss@icloud.com>
License: MIT License
Project-URL: Repository, https://github.com/rystrauss/dopamax.git
Classifier: Development Status :: 3 - Alpha
Classifier: License :: OSI Approved :: MIT License
Classifier: Programming Language :: Python :: 3.10
Classifier: Programming Language :: Python :: 3.11
Classifier: Programming Language :: Python :: 3.12
Classifier: Topic :: Scientific/Engineering :: Artificial Intelligence
Requires-Python: >=3.10
License-File: LICENSE
Requires-Dist: jax==0.4.38
Requires-Dist: jaxlib==0.4.38
Requires-Dist: chex>=0.1.87
Requires-Dist: brax>=0.11.0
Requires-Dist: click>=8.1.7
Requires-Dist: distrax>=0.1.5
Requires-Dist: dm-env>=1.6
Requires-Dist: dm-haiku>=0.0.13
Requires-Dist: pgx>=2.4.2
Requires-Dist: einops>=0.8.0
Requires-Dist: ffmpeg>=1.4
Requires-Dist: imageio>=2.25.1
Requires-Dist: mctx>=0.0.5
Requires-Dist: moviepy>=1.0.3
Requires-Dist: ml-collections>=0.1.1
Requires-Dist: optax>=0.2.4
Requires-Dist: numpy>=1.22.4
Requires-Dist: rlax>=0.1.6
Requires-Dist: tqdm>=4.64.1
Requires-Dist: wandb>=0.18.7
Requires-Dist: flashbax>=0.1.2
Requires-Dist: gymnax>=0.0.8
